LICENSE.txt
MANIFEST.in
README.rst
requirements.txt
setup.cfg
setup.py
vmwvro/__init__.py
vmwvro/clients.py
vmwvro/config.py
vmwvro/sessions.py
vmwvro/utils.py
vmwvro/workflows.py
vmwvro.egg-info/PKG-INFO
vmwvro.egg-info/SOURCES.txt
vmwvro.egg-info/dependency_links.txt
vmwvro.egg-info/not-zip-safe
vmwvro.egg-info/requires.txt
vmwvro.egg-info/top_level.txt