Metadata-Version: 1.1
Name: vmwvro
Version: 1.0.0b1
Summary: A simple Python library to interface with VMware vRealize Orchestrator
Home-page: https://pypi.python.org/pypi/vmwvro
Author: Lior P. Abitbol
Author-email: liorabitbol@gmail.com
License: MIT
Keywords: vmware vro orchestrator api development
Platform: UNKNOWN
Classifier: Development Status :: 4 - Beta
Classifier: Intended Audience :: Developers
Classifier: Topic :: Software Development :: Build Tools
Classifier: License :: OSI Approved :: MIT License
Classifier: Programming Language :: PythonProgramming Language :: Python :: 3.5
